[
  {
    "id": "repair_kit",
    "name": "Repair Kit",
    "mass_kg": 50.0,
    "volume_m3": 0.1
  },
  {
    "id": "thruster",
    "name": "Thruster",
    "mass_kg": 200.0,
    "volume_m3": 0.5
  },
  {
    "id": "fe_plate",
    "name": "Iron Plate",
    "mass_kg": 25.0,
    "volume_m3": 0.05
  },
  {
    "id": "structural_beam",
    "name": "Structural Beam",
    "mass_kg": 100.0,
    "volume_m3": 0.3
  },
  {
    "id": "hull_panel",
    "name": "Hull Panel",
    "mass_kg": 350.0,
    "volume_m3": 1.0
  },
  {
    "id": "advanced_repair_kit",
    "name": "Advanced Repair Kit",
    "mass_kg": 75.0,
    "volume_m3": 0.15
  },
  {
    "id": "module_mining_laser",
    "name": "Mining Laser",
    "mass_kg": 800.0,
    "volume_m3": 3.0
  },
  {
    "id": "module_cargo_expander",
    "name": "Cargo Expander",
    "mass_kg": 400.0,
    "volume_m3": 2.0
  },
  {
    "id": "module_survey_scanner",
    "name": "Survey Scanner",
    "mass_kg": 300.0,
    "volume_m3": 1.5
  },
  {
    "id": "module_basic_engine",
    "name": "Basic Engine",
    "mass_kg": 1200.0,
    "volume_m3": 4.0
  },
  {
    "id": "module_propellant_tank",
    "name": "Propellant Tank",
    "mass_kg": 600.0,
    "volume_m3": 3.0
  },
  {
    "id": "cast_fe_part",
    "name": "Cast Iron Part",
    "mass_kg": 30.0,
    "volume_m3": 0.05
  },
  {
    "id": "solar_cell",
    "name": "Solar Cell",
    "mass_kg": 15.0,
    "volume_m3": 0.08
  },
  {
    "id": "camera_module",
    "name": "Camera Module",
    "mass_kg": 10.0,
    "volume_m3": 0.05
  },
  {
    "id": "guidance_board",
    "name": "Guidance Board",
    "mass_kg": 5.0,
    "volume_m3": 0.02
  },
  {
    "id": "antenna_array",
    "name": "Antenna Array",
    "mass_kg": 25.0,
    "volume_m3": 0.3
  },
  {
    "id": "transponder",
    "name": "Transponder",
    "mass_kg": 8.0,
    "volume_m3": 0.04
  },
  {
    "id": "atomic_clock",
    "name": "Atomic Clock",
    "mass_kg": 12.0,
    "volume_m3": 0.03
  },
  {
    "id": "signal_processor",
    "name": "Signal Processor",
    "mass_kg": 6.0,
    "volume_m3": 0.02
  },
  {
    "id": "sensor_payload",
    "name": "Sensor Payload",
    "mass_kg": 40.0,
    "volume_m3": 0.2
  },
  {
    "id": "attitude_controller",
    "name": "Attitude Controller",
    "mass_kg": 20.0,
    "volume_m3": 0.1
  },
  {
    "id": "solid_fuel_grain",
    "name": "Solid Fuel Grain",
    "mass_kg": 150.0,
    "volume_m3": 0.3
  },
  {
    "id": "guidance_unit",
    "name": "Guidance Unit",
    "mass_kg": 20.0,
    "volume_m3": 0.05
  },
  {
    "id": "nozzle",
    "name": "Rocket Nozzle",
    "mass_kg": 80.0,
    "volume_m3": 0.2
  },
  {
    "id": "liquid_engine",
    "name": "Liquid Engine",
    "mass_kg": 500.0,
    "volume_m3": 1.0
  },
  {
    "id": "fuel_tank",
    "name": "Fuel Tank",
    "mass_kg": 300.0,
    "volume_m3": 2.0
  },
  {
    "id": "survey_satellite",
    "name": "Survey Satellite",
    "mass_kg": 500.0,
    "volume_m3": 5.0
  },
  {
    "id": "comm_relay",
    "name": "Communication Relay",
    "mass_kg": 800.0,
    "volume_m3": 8.0
  },
  {
    "id": "nav_beacon",
    "name": "Navigation Beacon",
    "mass_kg": 600.0,
    "volume_m3": 6.0
  },
  {
    "id": "science_platform",
    "name": "Science Platform",
    "mass_kg": 1200.0,
    "volume_m3": 12.0
  },
  {
    "id": "rocket_sounding",
    "name": "Sounding Rocket",
    "mass_kg": 500.0,
    "volume_m3": 5.0
  },
  {
    "id": "rocket_light",
    "name": "Light Launcher",
    "mass_kg": 2000.0,
    "volume_m3": 15.0
  },
  {
    "id": "rocket_medium",
    "name": "Medium Launcher",
    "mass_kg": 8000.0,
    "volume_m3": 40.0
  },
  {
    "id": "station_kit",
    "name": "Orbital Station Kit",
    "mass_kg": 5000.0,
    "volume_m3": 50.0
  },
  {
    "id": "outpost_kit",
    "name": "Outpost Deployment Kit",
    "mass_kg": 5000.0,
    "volume_m3": 30.0,
    "deploys_frame": "frame_outpost"
  },
  {
    "id": "industrial_hub_kit",
    "name": "Industrial Hub Deployment Kit",
    "mass_kg": 15000.0,
    "volume_m3": 90.0,
    "deploys_frame": "frame_industrial_hub"
  },
  {
    "id": "research_station_kit",
    "name": "Research Station Deployment Kit",
    "mass_kg": 10000.0,
    "volume_m3": 60.0,
    "deploys_frame": "frame_research_station"
  }
]
